bankcard-deal/__init__.py
bankcard-deal/data_deal.py
bankcard-deal/data_fenxi.py
bankcard-deal/data_get.py
bankcard-deal/mydf.py
pjhcode/__init__.py
pjhcode/data_deal.py
pjhcode/data_fenxi.py
pjhcode/data_get.py
pjhcode/mydf.py
pjhcode-1.0.0.dist-info/LICENSE
pjhcode-1.0.0.dist-info/METADATA
pjhcode-1.0.0.dist-info/WHEEL
pjhcode-1.0.0.dist-info/top_level.txt
pjhcode-1.0.0.dist-info/RECORD
